q_snippets/__init__.py
q_snippets/adversarial.py
q_snippets/class.py
q_snippets/data.py
q_snippets/generation_utils.py
q_snippets/losses.py
q_snippets/metrics.py
q_snippets/object.py
q_snippets/optim.py
q_snippets/pretrains.py
q_snippets/tensor_ops.py
Q_snippets_Qing25-0.0.8.dist-info/LICENSE
Q_snippets_Qing25-0.0.8.dist-info/METADATA
Q_snippets_Qing25-0.0.8.dist-info/WHEEL
Q_snippets_Qing25-0.0.8.dist-info/top_level.txt
Q_snippets_Qing25-0.0.8.dist-info/RECORD
