Metadata-Version: 2.1
Name: Q-snippets-Qing25
Version: 0.0.8
Summary: My working code snippets
Home-page: https://github.com/Qing25/Q-snippets
Author: Qing25
Author-email: 599098562@qq.com
Project-URL: Bug Tracker, https://github.com/Qing25/Q-snippets
Classifier: Programming Language :: Python :: 3
Classifier: License :: OSI Approved :: MIT License
Classifier: Operating System :: OS Independent
Requires-Python: >=3.8
License-File: LICENSE
